btc_cycles/__init__.py
btc_cycles/artist/__init__.py
btc_cycles/artist/artist.py
btc_cycles/artist/static.py
btc_cycles/artist/utils.py
btc_cycles/core/__init__.py
btc_cycles/core/bitcoin.py
btc_cycles/core/halvings.json
btc_cycles/core/halvings.py
btc_cycles/core/prices.py
btc_cycles/core/sources/__init__.py
btc_cycles/core/sources/cmc.py
btc_cycles/core/sources/source.py
btc_cycles-0.3.5.dist-info/LICENSE
btc_cycles-0.3.5.dist-info/METADATA
btc_cycles-0.3.5.dist-info/WHEEL
btc_cycles-0.3.5.dist-info/RECORD
