Metadata-Version: 2.3
Name: btc-cycles
Version: 0.3.5
Summary: Track Bitcoin price over halving cycles
License: MIT
Author: giocaizzi
Author-email: giocaizzi@gmail.com
Requires-Python: >=3.8.1,<4.0.0
Classifier: License :: OSI Approved :: MIT License
Classifier: Programming Language :: Python :: 3
Classifier: Programming Language :: Python :: 3.9
Classifier: Programming Language :: Python :: 3.10
Classifier: Programming Language :: Python :: 3.11
Classifier: Programming Language :: Python :: 3.12
Classifier: Programming Language :: Python :: 3.13
Requires-Dist: cryptocmd (>=0.6.4,<0.7.0)
Requires-Dist: cryptocompare (>=0.7.6,<0.8.0)
Requires-Dist: matplotlib (<3.8) ; python_version < "3.9"
Requires-Dist: matplotlib (>=3.8,<4.0) ; python_version >= "3.9" and python_version < "4.0"
Requires-Dist: pandas (<2.1) ; python_version < "3.9"
Requires-Dist: pandas (>=2.1,<3.0) ; python_version >= "3.9" and python_version < "4.0"
